README.rst
setup.py
py_release_tools/__init__.py
py_release_tools/commands.py
py_release_tools.egg-info/PKG-INFO
py_release_tools.egg-info/SOURCES.txt
py_release_tools.egg-info/dependency_links.txt
py_release_tools.egg-info/entry_points.txt
py_release_tools.egg-info/requires.txt
py_release_tools.egg-info/top_level.txt