Metadata-Version: 1.1
Name: py-release-tools
Version: 0.1.3
Summary: Python release tools
Home-page: https://github.com/mcrute/py_release_tools
Author: Mike Crute
Author-email: mcrute@gmail.com
License: UNKNOWN
Platform: UNKNOWN
Classifier: Development Status :: 5 - Production/Stable
Classifier: Environment :: Console
Classifier: Framework :: Setuptools Plugin
Classifier: Intended Audience :: Developers
Classifier: License :: OSI Approved :: MIT License
Classifier: Operating System :: OS Independent
Classifier: Programming Language :: Python :: 2
Classifier: Programming Language :: Python :: 3
Classifier: Topic :: Software Development :: Build Tools
Classifier: Topic :: Software Development :: Testing
